creopyson/__init__.py
creopyson/bom.py
creopyson/connection.py
creopyson/creo.py
creopyson/dimension.py
creopyson/drawing.py
creopyson/exceptions.py
creopyson/familytable.py
creopyson/feature.py
creopyson/file.py
creopyson/geometry.py
creopyson/interface.py
creopyson/layer.py
creopyson/note.py
creopyson/objects.py
creopyson/parameter.py
creopyson/server.py
creopyson/view.py
creopyson/windchill.py
creopyson-0.7.8.dist-info/AUTHORS.rst
creopyson-0.7.8.dist-info/LICENSE
creopyson-0.7.8.dist-info/METADATA
creopyson-0.7.8.dist-info/WHEEL
creopyson-0.7.8.dist-info/top_level.txt
creopyson-0.7.8.dist-info/RECORD
