Metadata-Version: 2.1
Name: creopyson
Version: 0.7.8
Summary: Python library for Creoson
Home-page: https://github.com/Zepmanbc/creopyson
Author: Benjamin C.
Author-email: zepman@gmail.com
License: MIT license
Keywords: creopyson
Classifier: Development Status :: 3 - Alpha
Classifier: Intended Audience :: Developers
Classifier: License :: OSI Approved :: MIT License
Classifier: Natural Language :: English
Classifier: Programming Language :: Python :: 3 :: Only
Classifier: Programming Language :: Python :: 3.8
Classifier: Programming Language :: Python :: 3.9
Classifier: Programming Language :: Python :: 3.10
Classifier: Programming Language :: Python :: 3.11
Requires-Python: >=3.8
License-File: LICENSE
License-File: AUTHORS.rst
Requires-Dist: requests
